{
    "tenantId": "pb",
    "moduleName": "Workflow",
    "BusinessServiceMasterConfig": [
      {
        "businessService": "NewTL",
        "active": "true",
        "isStatelevel": "true"
      }     ,
      {
        "businessService": "WS",
        "active": "true",
        "isStatelevel": "true"
      } 
      ,
      {
        "businessService": "PT",
        "active": "true",
        "isStatelevel": "true"
      } ,
      {
        "businessService": "SW",
        "active": "true",
        "isStatelevel": "true"
      }
      ,
      {
        "businessService": "PGR",
        "active": "true",
        "isStatelevel": "true"
      }  
      
    ]
  }
